GloPel/Calculations.py
GloPel/Calculations_Fitting.py
GloPel/Dialog_Residue.py
GloPel/Dialog_Validation.py
GloPel/GloPel.py
GloPel/GloPelMainGui.py
GloPel/GloPel_splashicon.png
GloPel/Manual_GloPel.pdf
GloPel/Regularization.py
GloPel/Residue_SubGUI.py
GloPel/Validation_Progress_Bar.py
GloPel/Validation_SubGUI.py
GloPel/Variable_Initialization.py
GloPel/Warning_BG_dim_FIT.py
GloPel/Warning_Validation.py
GloPel/__init__.py
GloPel/figure_handler.py
GloPel/icon.png
GloPel/icon_logo.ico
GloPel/icon_logo.jpg
GloPel-1.0.1a18.dist-info/LICENSE.txt
GloPel-1.0.1a18.dist-info/METADATA
GloPel-1.0.1a18.dist-info/WHEEL
GloPel-1.0.1a18.dist-info/entry_points.txt
GloPel-1.0.1a18.dist-info/top_level.txt
GloPel-1.0.1a18.dist-info/RECORD
